coders_to_iamc/__init__.py
coders_to_iamc/ca_system_parameters.py
coders_to_iamc/capacity_factors.py
coders_to_iamc/constants.py
coders_to_iamc/cost.py
coders_to_iamc/demand.py
coders_to_iamc/forecasted_annual_demand.py
coders_to_iamc/generation_cost_evolution.py
coders_to_iamc/generation_planning_reserve.py
coders_to_iamc/generators.py
coders_to_iamc/grid_cells.py
coders_to_iamc/hydro_greenfield.py
coders_to_iamc/hydro_pump_storage.py
coders_to_iamc/hydro_renewal.py
coders_to_iamc/nodes.py
coders_to_iamc/provincial_transfers.py
coders_to_iamc/storage.py
coders_to_iamc/technology_parameters.py
coders_to_iamc/transmission.py
coders_to_iamc/transmission_generic.py
coders_to_iamc-1.0.0.dist-info/METADATA
coders_to_iamc-1.0.0.dist-info/WHEEL
coders_to_iamc-1.0.0.dist-info/top_level.txt
coders_to_iamc-1.0.0.dist-info/RECORD
