Metadata-Version: 2.2
Name: coders_to_iamc
Version: 1.0.0
Summary: Scripts that pull data from the CODERS database and format it for use in the IAMC format
Home-page: https://gitlab.com/sesit/coders-to-iamc
Classifier: Programming Language :: Python :: 3
Classifier: Operating System :: OS Independent
Requires-Python: >=3.10
Requires-Dist: pandas==1.5.3
Dynamic: classifier
Dynamic: description
Dynamic: description-content-type
Dynamic: home-page
Dynamic: requires-dist
Dynamic: requires-python
Dynamic: summary
